[
  {
    "nt1": "B.DG303",
    "nt2": "C.DC314"
  },
  {
    "nt1": "B.DA304",
    "nt2": "C.DT313"
  },
  {
    "nt1": "B.DT305",
    "nt2": "C.DA312"
  },
  {
    "nt1": "B.DC306",
    "nt2": "C.DG311"
  },
  {
    "nt1": "B.DG307",
    "nt2": "C.DC310"
  },
  {
    "nt1": "B.DC308",
    "nt2": "C.DG309"
  },
  {
    "nt1": "B.DG301",
    "nt2": "B1.DC302"
  },
  {
    "nt1": "B.DC302",
    "nt2": "B1.DG301"
  },
  {
    "nt1": "B1.DG303",
    "nt2": "C1.DC314"
  },
  {
    "nt1": "B1.DA304",
    "nt2": "C1.DT313"
  },
  {
    "nt1": "B1.DT305",
    "nt2": "C1.DA312"
  },
  {
    "nt1": "B1.DC306",
    "nt2": "C1.DG311"
  },
  {
    "nt1": "B1.DG307",
    "nt2": "C1.DC310"
  },
  {
    "nt1": "B1.DC308",
    "nt2": "C1.DG309"
  }
]